{
    "map": "Creech",
    "nb_samples":3,
    "cam": {
        "top_limit": 120,
        "bot_limit": 1050,
        "depth": 53,
        "near_half_width": 3.5,
        "far_half_width": 21
    },
    "data": {
        "1.png":{
            "pos": "P2",
            "dir": -1,
            "hdg": 2,
            "seg": {
                "0-0-0": "None",
                "255-0-0": "P2",
                "0-255-0": "A2_P2_3",
                "0-0-255": "A2_P2_2",
                "255-255-0": "A2_P2_1"
            }
        },
        "2.png":{
            "pos": "A3",
            "dir": 1,
            "hdg": 272,
            "seg": {
                "0-0-0": "None",
                "255-0-0": "A3",
                "0-255-0": "A3_P3_2",
                "0-0-255": "A3_P3_1",
                "255-255-0": "A3_P3_3",
                "0-255-255": "A4",
                "255-0-255": "A4_F1_2",
                "255-255-255": "A4_F1_1"
            }
        },
        "3.png":{
            "pos": "A4",
            "dir": 1,
            "hdg": 271,
            "seg": {
                "0-0-0": "None",
                "255-0-0": "A4",
                "0-255-0": "A4_F1_1",
                "0-0-255": "A4_F1_2",
                "255-255-0": "A4_F1_3",
                "0-255-255": "A5"
            }
        }
    }
}